LICENSE
MANIFEST.in
README.rst
setup.py
django_git_brokenlink_track.egg-info/PKG-INFO
django_git_brokenlink_track.egg-info/SOURCES.txt
django_git_brokenlink_track.egg-info/dependency_links.txt
django_git_brokenlink_track.egg-info/requires.txt
django_git_brokenlink_track.egg-info/top_level.txt
django_git_brokenlink_track.egg-info/zip-safe
git_brokenlink_track/__init__.py
git_brokenlink_track/admin.py
git_brokenlink_track/apps.py
git_brokenlink_track/middleware.py
git_brokenlink_track/models.py
git_brokenlink_track/tests.py
git_brokenlink_track/views.py
git_brokenlink_track/migrations/__init__.py