Metadata-Version: 1.1
Name: django-git-brokenlink-track
Version: 1.1.dev
Summary: Django app which automates the issue creation on Git for broken links.
Home-page: https://github.com/tarunbehal/django-git-brokenlink-track
Author: Tarun Behal
Author-email: tarunbehal@hotmail.com
License: MIT
Keywords: git bug tracking django broken link
Platform: UNKNOWN
Classifier: Development Status :: 3 - Alpha
Classifier: Environment :: Web Environment
Classifier: Framework :: Django
Classifier: Intended Audience :: Developers
Classifier: License :: OSI Approved :: MIT License
Classifier: Operating System :: OS Independent
Classifier: Programming Language :: Python
Classifier: Programming Language :: Python :: 2
Classifier: Programming Language :: Python :: 2.6
Classifier: Programming Language :: Python :: 2.7
Classifier: Programming Language :: Python :: 3
Classifier: Programming Language :: Python :: 3.2
Classifier: Programming Language :: Python :: 3.3
Classifier: Programming Language :: Python :: 3.4
Classifier: Topic :: Software Development :: Debuggers
Classifier: Topic :: Software Development :: Bug Tracking
Classifier: Topic :: Internet :: WWW/HTTP :: Site Management
Classifier: Topic :: Internet :: WWW/HTTP :: Site Management :: Link Checking
Classifier: Topic :: Internet :: WWW/HTTP :: WSGI :: Middleware
Classifier: Topic :: Software Development :: Quality Assurance
